[
    {
        "employeeCode": "EMP001",
        "timestamp": "2026-01-15T08:55:00",
        "type": "IN"
    },
    {
        "employeeCode": "EMP001",
        "timestamp": "2026-01-15T17:35:00",
        "type": "OUT"
    },
    {
        "employeeCode": "EMP002",
        "timestamp": "2026-01-15T09:10:00",
        "type": "IN"
    },
    {
        "employeeCode": "EMP002",
        "timestamp": "2026-01-15T18:00:00",
        "type": "OUT"
    },
    {
        "employeeCode": "EMP003",
        "timestamp": "2026-01-15T08:00:00",
        "type": "IN"
    },
    {
        "employeeCode": "EMP003",
        "timestamp": "2026-01-15T17:00:00",
        "type": "OUT"
    },
    {
        "employeeCode": "EMP001",
        "timestamp": "2026-01-16T09:05:00",
        "type": "IN"
    },
    {
        "employeeCode": "EMP001",
        "timestamp": "2026-01-16T17:40:00",
        "type": "OUT"
    },
    {
        "employeeCode": "EMP002",
        "timestamp": "2026-01-16T08:50:00",
        "type": "IN"
    },
    {
        "employeeCode": "EMP002",
        "timestamp": "2026-01-16T17:55:00",
        "type": "OUT"
    },
    {
        "employeeCode": "EMP001",
        "timestamp": "2026-01-17T08:58:00",
        "type": "IN"
    },
    {
        "employeeCode": "EMP009",
        "timestamp": "2026-01-17T08:58:00",
        "type": "IN"
    }
]